{
    "table": {
        "columns": [
            [
                "column1"
            ],
            [
                "column2"
            ]
        ],
        "indexs": [
            "index"
        ],
        "values": [
            "data"
        ]
    },
    "sankey": {
        "node": [
            "data"
        ],
        "sources": [
            "data"
        ],
        "targets": [
            "data"
        ],
        "values": [
            "data"
        ]
    },
    "bar_chart": {
        "0": {
            "name": "checkin_A ??",
            "kpi": {
                "processed_passengers": 1,
                "average_processing_time": 1,
                "number_of_facilities": 1,
                "average_wait_time": 1,
                "maximum_wait_time": 1,
                "queue_capacity_limit": 1
            },
            "inflow": {
                "x": [
                    "data"
                ],
                "y": [
                    "data"
                ]
            },
            "outflow": {
                "x": [
                    "data"
                ],
                "y": [
                    "data"
                ]
            },
            "queuing": {
                "x": [
                    "data"
                ],
                "y": [
                    "data"
                ]
            }
        }
    }
}